MANIFEST.in
README.rst
setup.py
sharedmem/__init__.py
sharedmem/parallel.py
sharedmem/sharedmem.py
sharedmem.egg-info/PKG-INFO
sharedmem.egg-info/SOURCES.txt
sharedmem.egg-info/dependency_links.txt
sharedmem.egg-info/not-zip-safe
sharedmem.egg-info/requires.txt
sharedmem.egg-info/top_level.txt