Metadata-Version: 1.1
Name: sharedmem
Version: 0.3.5
Summary: Dispatch your trivially parallizable jobs with sharedmem. 
Home-page: http://github.com/rainwoodman/sharedmem
Author: Yu Feng
Author-email: rainwoodman@gmail.com
License: UNKNOWN
Platform: UNKNOWN
Requires: numpy
